filechex/__init__.py
filechex/checks.py
filechex-0.1.2.dist-info/METADATA
filechex-0.1.2.dist-info/RECORD
filechex-0.1.2.dist-info/WHEEL
filechex-0.1.2.dist-info/top_level.txt
tests/__init__.py
tests/test_sample.py
