Metadata-Version: 2.1
Name: filechex
Version: 0.1.2
Summary: A utility package designed to compare files to determine whether source files should be processed.
Home-page: https://github.com/cw-andrews/cookiecutter-pypackage-minimal
Author: cw-andrews
Author-email: cwandrews.oh@gmail.com
License: UNKNOWN
Platform: UNKNOWN
Classifier: Development Status :: 2 - Pre-Alpha
Classifier: Programming Language :: Python
Classifier: Programming Language :: Python :: 3.6
Classifier: Programming Language :: Python :: 3.7
